bertnlp/__init__.py
bertnlp/fuzzy.py
bertnlp/fuzzy_matcher.py
bertnlp/measure.py
bertnlp/pipeline.py
bertnlp/text_classifier.py
bertnlp/utils.py
bertnlp/data/heart_test_Aug2020.csv
bertnlp/data/heart_train_SeptNovDec2020.csv
bertnlp-0.0.7.dist-info/LICENSE
bertnlp-0.0.7.dist-info/METADATA
bertnlp-0.0.7.dist-info/WHEEL
bertnlp-0.0.7.dist-info/top_level.txt
bertnlp-0.0.7.dist-info/RECORD
