Metadata-Version: 2.1
Name: bertnlp
Version: 0.0.7
Summary: BERT toolkit is a Python package that performs various NLP tasks using Bidirectional Encoder Representations from Transformers (BERT) related models.
Home-page: UNKNOWN
Author: Shuanglu Dai
Author-email: shud@microsoft.com
License: UNKNOWN
Keywords: bertnlp
Platform: UNKNOWN
Classifier: Development Status :: 2 - Pre-Alpha
Classifier: Intended Audience :: Developers
Classifier: Natural Language :: English
Classifier: Programming Language :: Python :: 3.7
Classifier: Programming Language :: Python :: 3.8
Classifier: License :: OSI Approved :: MIT License
Requires-Dist: nltk (==3.2.5)
Requires-Dist: tensorflow (==2.3.1)
Requires-Dist: torch (==1.7.0+cpu)
Requires-Dist: sentencepiece (==0.1.94)
Requires-Dist: tokenizers (==0.8.1.rc2)
Requires-Dist: transformers (==3.3.0)
